ipynb_tests/__init__.py
ipynb_tests/tester.py
tests/__init__.py
tests/example.py
tests/test_tester.py
ipynb_tests-1.0rc1.dist-info/LICENSE
ipynb_tests-1.0rc1.dist-info/METADATA
ipynb_tests-1.0rc1.dist-info/WHEEL
ipynb_tests-1.0rc1.dist-info/top_level.txt
ipynb_tests-1.0rc1.dist-info/RECORD
