Metadata-Version: 2.1
Name: ipynb-tests
Version: 1.0rc1
Summary: Run Jupyter notebook tests
Home-page: https://bitbucket.org/coleopter/ipynb-tests
Author: Daniel Farré Manzorro
Author-email: d.farre.m@gmail.com
License: UNKNOWN
Platform: UNKNOWN
Classifier: Programming Language :: Python :: 3
Classifier: Programming Language :: Python :: 3.6
Classifier: License :: OSI Approved :: MIT License
Classifier: Operating System :: OS Independent
Classifier: Intended Audience :: Developers
Provides-Extra: test
Provides-Extra: dev
